syssimpymmen/__init__.py
syssimpymmen/mmen.py
syssimpymmen/data/MR_earthlike_rocky.txt
syssimpymmen/data/MR_pure_iron.txt
syssimpymmen/data/MRpredict_table_weights3025_R1001_Q1001.txt
syssimpymmen-1.0.0.dist-info/LICENSE
syssimpymmen-1.0.0.dist-info/METADATA
syssimpymmen-1.0.0.dist-info/WHEEL
syssimpymmen-1.0.0.dist-info/top_level.txt
syssimpymmen-1.0.0.dist-info/RECORD
