Metadata-Version: 2.1
Name: syssimpymmen
Version: 1.0.0
Summary: A framework for inferring the Minimum Mass Extrasolar Nebula (MMEN) from the SysSim Clustered Planetary System Models
Author-email: Matthias Yang He <mhe@nd.edu>
License: MIT License        
Project-URL: Homepage, https://syssimpymmen.readthedocs.io
Project-URL: Source, https://github.com/hematthi/SysSimPyMMEN
Project-URL: Bug Tracker, https://github.com/hematthi/SysSimPyMMEN/issues
Classifier: Programming Language :: Python :: 3
Classifier: License :: OSI Approved :: MIT License
Classifier: Operating System :: OS Independent
Classifier: Intended Audience :: Science/Research
Requires-Python: >=3.7
License-File: LICENSE
